[{"word": "marble", "ipa": "/ˈmɑːbl/", "explain": [{"cn": "n. 大理石；弹子； [pl.] 弹子游戏"}]}, {"word": "booth", "ipa": "/buːð/", "explain": [{"cn": "n. （隔开的）小房间；公用电话亭；售货棚"}]}, {"word": "imitation", "ipa": "/ˏɪmɪˈteɪʃn/", "explain": [{"cn": "n. 模仿；仿造；仿制品，假货，赝品"}]}, {"word": "exceed", "ipa": "/ɪkˈsiːd/", "explain": [{"cn": "v. 超过，胜过"}]}, {"word": "cohesion", "ipa": "/kəuˈhiːʒn/", "explain": [{"cn": "v. 结合，团结；凝聚力"}]}, {"word": "astound", "ipa": "/əˈstaund/", "explain": [{"cn": "v. （使）震惊"}]}, {"word": "absorb", "ipa": "/əbˈsɔːb/", "explain": [{"cn": "v. 吸收；吸引……的注意，使全神贯注；把……并入，同化"}]}, {"word": "livestock", "ipa": "/ˈlaɪvstɔk/", "explain": [{"cn": "n. <总称> 家畜，牲畜"}]}, {"word": "decrease", "ipa": "/dɪˈkriːs/", "explain": [{"cn": "v. 减少，减小  /ˈdiːkriːs/ n. 减少；减少量"}]}, {"word": "moral", "ipa": "/ˈmɔrəl/", "explain": [{"cn": "a. 道德的，伦理的  n. [pl.] 品行，道德；寓意，教训"}]}, {"word": "weigh", "ipa": "/weɪ/", "explain": [{"cn": "v. 称重；认真考虑，权衡"}]}, {"word": "ceramic", "ipa": "[səˈræmɪk]", "explain": [{"cn": "a. 陶器的  n. [pl.] 陶瓷器"}]}, {"word": "acquisition", "ipa": "/ˏækwɪˈzɪʃn/", "explain": [{"cn": "n. 取得；获得物"}]}, {"word": "character", "ipa": "/ˈkærəktə(r)/", "explain": [{"cn": "n. 性格，品质；性质，特性；人物，角色；（书写或印刷）符号，（汉）字"}]}, {"word": "arrange", "ipa": "/əˈreɪndʒ/", "explain": [{"cn": "v. 安排；排列"}]}, {"word": "conservation", "ipa": "/ˏkɔnsəˈveɪʃn/", "explain": [{"cn": "n. 保存；保护"}]}, {"word": "earthworm", "ipa": "[ˈɜ:θˌwɜ:m]", "explain": [{"cn": "n. 蚯蚓；小人"}]}, {"word": "entice", "ipa": "/ɪnˈtaɪs/", "explain": [{"cn": "v. 怂恿，引诱"}]}, {"word": "manipulative", "ipa": "[mə'nɪpjələtɪv]", "explain": [{"cn": "a. 操纵别人的；老于世故的"}]}, {"word": "memorise", "ipa": "/ˈmeməraɪz/", "explain": [{"cn": "vt. 记住，熟记"}]}, {"word": "retrenchment", "ipa": "[rɪ'trentʃmənt]", "explain": [{"cn": "n. 节省；削减"}]}, {"word": "motivational", "ipa": "[ˌməʊtɪ'veɪʃənl]", "explain": [{"cn": "a. 动机的，有关动机的"}]}, {"word": "reinforcement", "ipa": "[ˌri:ɪn'fɔ:smənt]", "explain": [{"cn": "n. 增援，加强，加固"}]}, {"word": "intervention", "ipa": "[ˌɪntə'venʃn]", "explain": [{"cn": "n. 干涉，干预，介入"}]}, {"word": "infirmity", "ipa": "[ɪn'fɜ:mətɪ]", "explain": [{"cn": "n. 虚弱，衰弱"}]}, {"word": "glossy", "ipa": "['ɡlɒsɪ]", "explain": [{"cn": "a. 有光泽的，光滑的"}]}, {"word": "escalate", "ipa": "/ˈeskəleɪt/", "explain": [{"cn": "v. （使）逐步增长或发展，（使）逐步升级"}]}, {"word": "extravagance", "ipa": "[ɪkˈstrævəgəns]", "explain": [{"cn": "n. 奢侈，挥霍；放肆的言行"}]}, {"word": "victimise", "ipa": "/ˈvɪktɪmaɪz/", "explain": [{"cn": "v. （使）受害，迫害"}]}, {"word": "evaluation", "ipa": "[ɪˌvæljʊ'eɪʃn]", "explain": [{"cn": "n. 估价，评价"}]}, {"word": "maternal", "ipa": "/məˈtɜːnl/", "explain": [{"cn": "a. 母亲的；母系的"}]}, {"word": "crusade", "ipa": "/kruːˈseɪd/", "explain": [{"cn": "n. 十字军（远征）；斗争，运动  v. 加入十字军，投身正义运动"}]}, {"word": "recalcitrant", "ipa": "/rɪˈkælsɪtrənt/", "explain": [{"cn": "a. 顽抗的，反抗的"}]}, {"word": "mortality", "ipa": "/mɔːˈtælətɪ/", "explain": [{"cn": "n. 死亡率"}]}, {"word": "taunt", "ipa": "/tɔːnt/", "explain": [{"cn": "vt. 嘲笑，讥笑  n. [常pl.] 嘲弄的言语，讥讽"}]}, {"word": "disseminate", "ipa": "/dɪˈsemɪneɪt/", "explain": [{"cn": "v. 散布，传播"}]}, {"word": "sanction", "ipa": "/ˈsæŋkʃn/", "explain": [{"cn": "v. 批准，认可  n. 批准，认可；约束因素，约束力；[常pl.] 国际制裁"}]}, {"word": "frustration", "ipa": "[frʌ'streɪʃn]", "explain": [{"cn": "n. 沮丧，不满"}]}, {"word": "invert", "ipa": "/ɪnˈvɜːt/", "explain": [{"cn": "vt. （使）倒转，（使）颠倒"}]}, {"word": "recipe", "ipa": "/ˈresəpɪ/", "explain": [{"cn": "n. 食谱；方法，秘诀，秘方"}]}, {"word": "condense", "ipa": "/kənˈdens/", "explain": [{"cn": "v. （使）压缩，精简；（使）凝结"}]}, {"word": "unfortunately", "ipa": "[ʌnˈfɔ:tʃənətli]", "explain": [{"cn": "ad. 不幸地"}]}, {"word": "gather", "ipa": "/ˈgæðə(r)/", "explain": [{"cn": "v. 聚焦，集合，聚拢；收集，采集；逐渐增加；猜想，推测"}]}, {"word": "Cantonese", "ipa": "/ˏkæntəˈniːz/", "explain": [{"cn": "n. a. 广东人（的）；广东话（的）"}]}, {"word": "advertise", "ipa": "/ˈædvətaɪz/", "explain": [{"cn": "vt. 为……做广告；宣传；（在报刊、电视、广播中）公告，公布"}]}, {"word": "utility", "ipa": "/juːˈtɪlətɪ/", "explain": [{"cn": "n. 功用，效用； [常pl.] 公用事业"}]}, {"word": "exhibit", "ipa": "/ɪgˈzɪbɪt/", "explain": [{"cn": "n. 展览品  v. 陈列，展览；显示"}]}, {"word": "irrevocable", "ipa": "/ɪˈrevəkəbl/", "explain": [{"cn": "a. 无法取消的，不能改变的"}]}, {"word": "shelter", "ipa": "/ˈʃeltə(r)/", "explain": [{"cn": "n. 掩蔽（处），隐蔽（处）；住所；保护  v. 掩蔽；躲避"}]}, {"word": "stock", "ipa": "/stɔk/", "explain": [{"cn": "n. 储备品；股票； <总称> 家畜  v. 储备  a. 常备的"}]}, {"word": "devise", "ipa": "/dɪˈvaɪz/", "explain": [{"cn": "vt. 设计，发明"}]}, {"word": "career", "ipa": "/kəˈrɪə(r)/", "explain": [{"cn": "n. 生涯；经历；职业"}]}, {"word": "humidity", "ipa": "[hju:ˈmɪdəti]", "explain": [{"cn": "n. 湿度；潮湿"}]}, {"word": "hollow", "ipa": "/ˈhɔləu/", "explain": [{"cn": "a. 空的，空洞的；（声音）沉闷的；虚伪的，空虚的  v. 挖空，凿空"}]}, {"word": "statistic", "ipa": "[stəˈtɪstɪk]", "explain": [{"cn": "n. 统计数值；统计学"}]}, {"word": "bark", "ipa": "/bɑːk/", "explain": [{"cn": "vi. 吠叫  n. 犬吠声；树皮"}]}, {"word": "burrow", "ipa": "/ˈbʌrəu/", "explain": [{"cn": "v. 挖掘，钻进；翻寻  n. 地洞"}]}, {"word": "equivalent", "ipa": "/ɪˈkwɪvələnt/", "explain": [{"cn": "a. 相等的，等量的  n. 相等物，等价物"}]}, {"word": "fatigue", "ipa": "/fəˈtiːg/", "explain": [{"cn": "n. 疲劳，劳累  v. （使）疲劳"}]}, {"word": "bibliography", "ipa": "/ˏbɪblɪˈɔgrəfɪ/", "explain": [{"cn": "n. 参考书目；书目；文献学"}]}, {"word": "probable", "ipa": "/ˈprɔbəbl/", "explain": [{"cn": "a. 很可能的，大概的"}]}, {"word": "fortnight", "ipa": "/ˈfɔːtnaɪt/", "explain": [{"cn": "n. 两星期，十四天"}]}, {"word": "treadmill", "ipa": "[ˈtredmɪl]", "explain": [{"cn": "n. （人或畜力的）踏车；累人的活；单调的例行工作，乏味繁重的工作"}]}, {"word": "flavour", "ipa": "/ˈfleɪvə(r)/", "explain": [{"cn": "n. 风味，滋味  vt. 给……调味"}]}, {"word": "asymmetry", "ipa": "[ˌeɪ'sɪmətrɪ]", "explain": [{"cn": "n. 不对称"}]}, {"word": "lethal", "ipa": "/ˈliːθl/", "explain": [{"cn": "a. 致命的，破坏性的，毁灭性的；有害的"}]}, {"word": "stare", "ipa": "/steə(r)/", "explain": [{"cn": "n. vi. 盯"}]}, {"word": "bungalow", "ipa": "/ˈbʌŋgələu/", "explain": [{"cn": "n. （带走廊的）平房"}]}, {"word": "colony", "ipa": "/ˈkɔlənɪ/", "explain": [{"cn": "n. 殖民地；（动植物的）群体"}]}, {"word": "stab", "ipa": "[stæb]", "explain": [{"cn": "v. 刺，戳"}]}, {"word": "fingerprint", "ipa": "['fɪŋɡəprɪnt]", "explain": [{"cn": "n. 指纹，手印"}]}, {"word": "enthusiasm", "ipa": "/ɪnˈθjuːzɪæzəm/", "explain": [{"cn": "n. 热情，热心，积极性；热衷的事物"}]}, {"word": "briefly", "ipa": "[ˈbri:fli]", "explain": [{"cn": "ad. 暂时地；简要地"}]}, {"word": "flint", "ipa": "/flɪnt/", "explain": [{"cn": "n. 火石，打火石"}]}, {"word": "commodity", "ipa": "/kəˈmɔdətɪ/", "explain": [{"cn": "n. 商品，货物；日用品"}]}]